sphinxcontrib_analytics_hub-0.0.3.dist-info/METADATA
sphinxcontrib_analytics_hub-0.0.3.dist-info/WHEEL
sphinxcontrib_analytics_hub/__init__.py
sphinxcontrib_analytics_hub/__version__.py
sphinxcontrib_analytics_hub/analytics.py
sphinxcontrib_analytics_hub/const.py
sphinxcontrib_analytics_hub-0.0.3.dist-info/RECORD
