Metadata-Version: 2.1
Name: sphinxcontrib-analytics-hub
Version: 0.0.3
Summary: Sphinx extension for googleanalytics and baiduanalytics
Home-page: https://github.com/un4gt/sphinxcontrib-analytics-hub
Author-Email: un4gt <mt3085570450@outlook.com>
License: MIT
Project-URL: Homepage, https://github.com/un4gt/sphinxcontrib-analytics-hub
Requires-Python: >=3.11
Requires-Dist: sphinx>=7.3.7
